smartbuildsim/__init__.py
smartbuildsim/bim/__init__.py
smartbuildsim/bim/loader.py
smartbuildsim/bim/schema.py
smartbuildsim/cli/__init__.py
smartbuildsim/cli/app.py
smartbuildsim/config/__init__.py
smartbuildsim/config/determinism.py
smartbuildsim/data/__init__.py
smartbuildsim/data/generator.py
smartbuildsim/data/validation.py
smartbuildsim/evaluation/__init__.py
smartbuildsim/evaluation/benchmark.py
smartbuildsim/features/__init__.py
smartbuildsim/features/engineering.py
smartbuildsim/logging/__init__.py
smartbuildsim/logging/config.py
smartbuildsim/models/__init__.py
smartbuildsim/models/anomaly.py
smartbuildsim/models/clustering.py
smartbuildsim/models/forecasting.py
smartbuildsim/models/rl.py
smartbuildsim/scenarios/__init__.py
smartbuildsim/scenarios/presets.py
smartbuildsim/utils/__init__.py
smartbuildsim/utils/helpers.py
smartbuildsim/viz/__init__.py
smartbuildsim/viz/plots.py
smartbuildsim-0.2.0.dist-info/licenses/LICENSE
smartbuildsim-0.2.0.dist-info/METADATA
smartbuildsim-0.2.0.dist-info/WHEEL
smartbuildsim-0.2.0.dist-info/entry_points.txt
smartbuildsim-0.2.0.dist-info/top_level.txt
smartbuildsim-0.2.0.dist-info/RECORD
