Metadata-Version: 2.4
Name: smartbuildsim
Version: 0.2.0
Summary: Synthetic smart building simulation toolkit with CLI workflows
Author: SmartBuildSim Team
License: MIT License
Project-URL: homepage, https://example.com/smartbuildsim
Project-URL: documentation, https://example.com/smartbuildsim/docs
Classifier: Programming Language :: Python :: 3
Classifier: License :: OSI Approved :: MIT License
Classifier: Operating System :: OS Independent
Requires-Python: >=3.10
License-File: LICENSE
Requires-Dist: joblib>=1.3
Requires-Dist: matplotlib>=3.7
Requires-Dist: numpy>=1.24
Requires-Dist: pandas>=2.0
Requires-Dist: pydantic<3,>=1.10
Requires-Dist: PyYAML>=6.0
Requires-Dist: scikit-learn>=1.2
Requires-Dist: typer[all]>=0.9
Provides-Extra: dev
Requires-Dist: mypy>=1.8; extra == "dev"
Requires-Dist: pytest>=7.4; extra == "dev"
Requires-Dist: pytest-cov>=4.1; extra == "dev"
Requires-Dist: ruff>=0.2; extra == "dev"
Dynamic: license-file
